[
  {
    "id": 1777872448723,
    "title": "플랜트 AI 스타트업 시냅스케일 창업자 커피챗 인터뷰 분석",
    "desc": "엔지니어 출신 공동창업자가 플랜트 산업 특화 온톨로지 기반 AI 설계 자동화 스타트업 시냅스케일을 창업하며 글로벌 컨설턴트 멘토와 나눈 커피챗. 피칭 전략, 가치사슬 포지셔닝, 창업 생태계 조언을 심층 분석한다.",
    "category": "전략",
    "tags": [
      "플랜트AI",
      "온톨로지",
      "스타트업창업",
      "P&ID자동화",
      "엔지니어링AI",
      "시냅스케일",
      "커피챗멘토링"
    ],
    "date": "2026-05-04",
    "emoji": "🏭",
    "url": "pages/2026-05-04_26b2b0.html"
  },
  {
    "id": 1777867039391,
    "title": "엄태성 선배님 커피챗 롤플레이 가이드 | SnapScale",
    "desc": "",
    "category": "기타",
    "tags": [],
    "date": "2026-05-04",
    "emoji": "📄",
    "url": "pages/2026-05-04_roleplay_eom_coffeechat_11.html"
  },
  {
    "id": 1777860802462,
    "title": "SnapScale 가격정책 결정 요약 | One Pager v4.0",
    "desc": "",
    "category": "전략",
    "tags": [
      "가격정책"
    ],
    "date": "2026-05-04",
    "emoji": "📄",
    "url": "pages/2026-05-04_SnapScale_One_Pager_1777860777659.html"
  },
  {
    "id": 1777707156323,
    "title": "회의록 | 신의스케일 전체 진행 현황 보고",
    "desc": "",
    "category": "기타",
    "tags": [],
    "date": "2026-05-02",
    "emoji": "📄",
    "url": "pages/2026-05-01_1777703293781.html"
  },
  {
    "id": 1777631046551,
    "title": "초기 투자자가 꼭 알아야 할 것들 — 퓨처플레이 권호영 대표 강의",
    "desc": "퓨처플레이 권호영 대표가 초기 벤처투자자를 위해 공유한 시장 이해, 스타트업 생태계, 투자 철학, 창업팀 평가 기준에 관한 심층 강의를 분석한 리포트. 파도 타기 이론부터 Unfair Advantage 개념, 셰르파 역할론까지 실전 인사이트를 담았다.",
    "category": "투자",
    "tags": [
      "벤처투자",
      "초기투자",
      "퓨처플레이",
      "스타트업생태계",
      "투자철학"
    ],
    "date": "2026-05-01",
    "emoji": "🚀",
    "url": "pages/2026-05-01_1ce611.html"
  },
  {
    "id": 1777605565586,
    "title": "2026-05-01 김상윤대표 미팅",
    "desc": "",
    "category": "전략",
    "tags": [
      "CEO미팅"
    ],
    "date": "2026-05-01",
    "emoji": "✅",
    "url": "pages/2026-05-01_985a43.html"
  },
  {
    "id": 1,
    "title": "투자지주 특강 분석",
    "desc": "서울대 기술지주 심상우 팀장 + 탭앤젤 파트너스 주진영 부대표의 스타트업 투자 생태계 및 TIPS 프로그램 심층 분석. 슬라이드 갤러리 + VC·창업가 관점 포함.",
    "category": "투자",
    "tags": [
      "투자",
      "TIPS",
      "세미나",
      "스타트업",
      "AC",
      "VC",
      "투자생태계"
    ],
    "date": "2026-04-30",
    "emoji": "📊",
    "url": "pages/af3908.html"
  },
  {
    "id": 2,
    "title": "SnapScale 공동창업 협업 증거 대시보드",
    "desc": "박규호 부장 30% 지분 정당성 증거 대시보드. 9개월 48회 회의, 5개 기여 영역, 32개 미팅 기록, 투자자 Q&A 20문항 포함.",
    "category": "IR",
    "tags": [
      "IR",
      "SnapScale",
      "공동창업",
      "지분",
      "씨드투자",
      "협업증거"
    ],
    "date": "2026-04-28",
    "emoji": "🤝",
    "url": "pages/snapscale.html"
  }
]